README.rst
setup.py
kaadbg/__init__.py
kaadbg/debug.py
kaadbg/run.py
kaadbg.egg-info/PKG-INFO
kaadbg.egg-info/SOURCES.txt
kaadbg.egg-info/dependency_links.txt
kaadbg.egg-info/top_level.txt