Metadata-Version: 1.1
Name: kaadbg
Version: 0.3.0
Summary: Remote debugger runner for kaa
Home-page: https://github.com/kaaedit/kaadbg
Author: Atsuo Ishimoto
Author-email: ishimoto@gembook.org
License: MIT License
Platform: UNKNOWN
Classifier: Programming Language :: Python :: 2
Classifier: Programming Language :: Python :: 3
Classifier: Development Status :: 3 - Alpha
Classifier: Topic :: Text Editors
Classifier: Topic :: Software Development :: Debuggers
Classifier: Environment :: Console :: Curses
Classifier: License :: OSI Approved :: MIT License
